npycomp/__init__.py
npycomp/_include/__init__.py
npycomp/_include/_graph.py
npycomp/problems/_3sat.py
npycomp/problems/__init__.py
npycomp/problems/_clique.py
npycomp/problems/_ilp.py
npycomp/problems/_problem.py
npycomp/problems/_sat.py
npycomp/problems/_sat_solver.py
npycomp/reductions/_3sat_to_clique.py
npycomp/reductions/_3sat_to_sat.py
npycomp/reductions/__init__.py
npycomp/reductions/_clique_to_sat.py
npycomp/reductions/_directory.py
npycomp-0.2.0.dist-info/LICENSE
npycomp-0.2.0.dist-info/METADATA
npycomp-0.2.0.dist-info/WHEEL
npycomp-0.2.0.dist-info/top_level.txt
npycomp-0.2.0.dist-info/RECORD
